carculator_truck/__init__.py
carculator_truck/driving_cycles.py
carculator_truck/inventory.py
carculator_truck/model.py
carculator_truck/truck_input_parameters.py
carculator_truck/data/default_parameters.json
carculator_truck/data/extra_parameters.json
carculator_truck/data/payloads.yaml
carculator_truck-0.5.0.dist-info/LICENSE
carculator_truck-0.5.0.dist-info/METADATA
carculator_truck-0.5.0.dist-info/WHEEL
carculator_truck-0.5.0.dist-info/top_level.txt
carculator_truck-0.5.0.dist-info/RECORD
