Metadata-Version: 2.1
Name: carculator_truck
Version: 0.5.0
Summary: Prospective environmental and economic life cycle assessmentof medium and heavy goods vehicles
Home-page: https://github.com/romainsacchi/carculator_truck
Author: Romain Sacchi <romain.sacchi@psi.ch>
License: BSD 3-Clause License
Classifier: Intended Audience :: End Users/Desktop
Classifier: Intended Audience :: Developers
Classifier: Intended Audience :: Science/Research
Classifier: License :: OSI Approved :: BSD License
Classifier: Operating System :: MacOS :: MacOS X
Classifier: Operating System :: Microsoft :: Windows
Classifier: Operating System :: POSIX
Classifier: Programming Language :: Python
Classifier: Programming Language :: Python :: 3
Classifier: Programming Language :: Python :: 3.5
Classifier: Programming Language :: Python :: 3.6
Classifier: Programming Language :: Python :: 3.7
Classifier: Programming Language :: Python :: 3.8
Classifier: Topic :: Scientific/Engineering :: Information Analysis
Classifier: Topic :: Scientific/Engineering :: Mathematics
Classifier: Topic :: Scientific/Engineering :: Visualization
Requires-Python: >=3.10
License-File: LICENSE
Requires-Dist: carculator-utils >=1.3.0
Requires-Dist: prettytable
